dnstap_pb/__init__.py
dnstap_pb/dnstap_pb2.py
dnstap_pb-0.11.3.dist-info/LICENSE
dnstap_pb-0.11.3.dist-info/METADATA
dnstap_pb-0.11.3.dist-info/WHEEL
dnstap_pb-0.11.3.dist-info/top_level.txt
dnstap_pb-0.11.3.dist-info/RECORD
