Metadata-Version: 2.2
Name: dnstap_pb
Version: 0.11.3
Summary: Dnstap Protocol Buffers implementation in Python
Home-page: https://github.com/dmachard/python-dnstap-protobuf
Author: Denis MACHARD
Author-email: d.machard@gmail.com
Keywords: dnstap protobuf decoder encoder
Platform: any
Classifier: License :: OSI Approved :: MIT License
Classifier: Programming Language :: Python :: 3
Classifier: Operating System :: OS Independent
Classifier: Topic :: Software Development :: Libraries
License-File: LICENSE
Requires-Dist: protobuf
Dynamic: author
Dynamic: author-email
Dynamic: classifier
Dynamic: description
Dynamic: description-content-type
Dynamic: home-page
Dynamic: keywords
Dynamic: platform
Dynamic: requires-dist
Dynamic: summary
